serial4t/__init__.py
序列模組/__init__.py
serial4t-0.0.1.dist-info/LICENSE
serial4t-0.0.1.dist-info/METADATA
serial4t-0.0.1.dist-info/WHEEL
serial4t-0.0.1.dist-info/top_level.txt
serial4t-0.0.1.dist-info/RECORD
