Metadata-Version: 2.1
Name: serial4t
Version: 0.0.1
Summary: Computer Vision wrapper for Teenagers
Home-page: https://github.com/beardad1975/serial4t
Author: Wen-Hung, Chang 張文宏
Author-email: beardad1975@nmes.tyc.edu.tw
License: UNKNOWN
Platform: Windows
Classifier: Programming Language :: Python :: 3
Classifier: License :: OSI Approved :: MIT License
Classifier: Operating System :: Microsoft :: Windows
Classifier: Natural Language :: Chinese (Traditional)
Requires-Python: >=3.5
Requires-Dist: pyserial (>=3.4)
